cumulus_etl/__init__.py
cumulus_etl/batching.py
cumulus_etl/cli.py
cumulus_etl/cli_utils.py
cumulus_etl/common.py
cumulus_etl/errors.py
cumulus_etl/id_handling.py
cumulus_etl/store.py
cumulus_etl/completion/__init__.py
cumulus_etl/completion/schema.py
cumulus_etl/deid/__init__.py
cumulus_etl/deid/codebook.py
cumulus_etl/deid/ms-config.json
cumulus_etl/deid/mstool.py
cumulus_etl/deid/philter-config.toml
cumulus_etl/deid/philter.py
cumulus_etl/deid/scrubber.py
cumulus_etl/etl/__init__.py
cumulus_etl/etl/cli.py
cumulus_etl/etl/config.py
cumulus_etl/etl/context.py
cumulus_etl/etl/pipeline.py
cumulus_etl/etl/convert/__init__.py
cumulus_etl/etl/convert/cli.py
cumulus_etl/etl/init/__init__.py
cumulus_etl/etl/init/cli.py
cumulus_etl/etl/nlp/__init__.py
cumulus_etl/etl/nlp/cli.py
cumulus_etl/etl/studies/README.md
cumulus_etl/etl/studies/__init__.py
cumulus_etl/etl/studies/covid_symptom/__init__.py
cumulus_etl/etl/studies/covid_symptom/covid_ctakes.py
cumulus_etl/etl/studies/covid_symptom/covid_tasks.py
cumulus_etl/etl/studies/example/age.json
cumulus_etl/etl/studies/example/tasks.toml
cumulus_etl/etl/studies/example/ndjson/docref.ndjson.gz
cumulus_etl/etl/studies/example/ndjson/dxreport.ndjson.gz
cumulus_etl/etl/studies/glioma/case.json
cumulus_etl/etl/studies/glioma/tasks.toml
cumulus_etl/etl/studies/irae/donor.json
cumulus_etl/etl/studies/irae/history.json
cumulus_etl/etl/studies/irae/longitudinal.json
cumulus_etl/etl/studies/irae/meds.json
cumulus_etl/etl/studies/irae/tasks.toml
cumulus_etl/etl/tasks/__init__.py
cumulus_etl/etl/tasks/base.py
cumulus_etl/etl/tasks/basic_tasks.py
cumulus_etl/etl/tasks/nlp_task.py
cumulus_etl/etl/tasks/task_factory.py
cumulus_etl/export/__init__.py
cumulus_etl/export/cli.py
cumulus_etl/fhir/__init__.py
cumulus_etl/fhir/fhir_client.py
cumulus_etl/fhir/fhir_utils.py
cumulus_etl/formats/__init__.py
cumulus_etl/formats/base.py
cumulus_etl/formats/batch.py
cumulus_etl/formats/batched_files.py
cumulus_etl/formats/deltalake.py
cumulus_etl-3.12.3.dist-info/entry_points.txt
cumulus_etl-3.12.3.dist-info/licenses/LICENSE
cumulus_etl-3.12.3.dist-info/WHEEL
cumulus_etl-3.12.3.dist-info/METADATA
cumulus_etl-3.12.3.dist-info/RECORD
