Metadata-Version: 2.4
Name: cumulus-etl
Version: 3.12.3
Summary: Turns FHIR data into de-identified & aggregated records
Author-email: "Andy McMurry, PhD" <andrew.mcmurry@childrens.harvard.edu>, Michael Terry <michael.terry@childrens.harvard.edu>
Requires-Python: >= 3.11
License-Expression: Apache-2.0
Classifier: Operating System :: OS Independent
Classifier: Programming Language :: Python :: 3
Classifier: Topic :: Software Development :: Libraries :: Python Modules
License-File: LICENSE
Requires-Dist: aiobotocore >= 3
Requires-Dist: boto3 >= 1.34.131
Requires-Dist: ctakesclient >= 5.1
Requires-Dist: cumulus-fhir-support >= 1.8
Requires-Dist: delta-spark >= 4, < 5
Requires-Dist: fsspec[http, s3]
Requires-Dist: httpx
Requires-Dist: inscriptis
Requires-Dist: jambo >= 0.1.7
Requires-Dist: label-studio-sdk >= 2
Requires-Dist: nltk >= 3.9
Requires-Dist: openai
Requires-Dist: oracledb
Requires-Dist: philter-lite
Requires-Dist: pyarrow
Requires-Dist: pyathena
Requires-Dist: pydantic
Requires-Dist: pyspark < 4.1
Requires-Dist: rich
Requires-Dist: pre-commit ; extra == "dev"
Requires-Dist: ruff < 0.15 ; extra == "dev"
Requires-Dist: coverage ; extra == "tests"
Requires-Dist: ddt ; extra == "tests"
Requires-Dist: jwcrypto ; extra == "tests"
Requires-Dist: moto[server, s3] >= 5.0 ; extra == "tests"
Requires-Dist: pytest ; extra == "tests"
Requires-Dist: pytest-cov ; extra == "tests"
Requires-Dist: respx ; extra == "tests"
Requires-Dist: time-machine ; extra == "tests"
Project-URL: Homepage, https://github.com/smart-on-fhir/cumulus-etl
Provides-Extra: dev
Provides-Extra: tests
